{"name": "We think, We pedal", "date": "2025-11-18", "duration": 3600, "description": "60-minute structured workout with builds, single-leg drills, overgear/fast cadence intervals, and high-intensity Z6 work", "intervals": [{"name": "Easy Warm-up", "power_zone": "Z1", "cadence": null, "duration": 300, "notes": ""}, {"name": "Builds - Z3", "power_zone": "Z3", "cadence": 95, "duration": 30, "notes": ""}, {"name": "Builds - Z2", "power_zone": "Z2", "cadence": null, "duration": 120, "notes": ""}, {"name": "Builds - Z4", "power_zone": "Z4", "cadence": 95, "duration": 30, "notes": ""}, {"name": "Builds - Z3", "power_zone": "Z3", "cadence": null, "duration": 120, "notes": ""}, {"name": "Builds - Z5", "power_zone": "Z5", "cadence": 95, "duration": 30, "notes": ""}, {"name": "Builds - Z4", "power_zone": "Z4", "cadence": null, "duration": 120, "notes": ""}, {"name": "Recovery", "power_zone": "Z2", "cadence": null, "duration": 120, "notes": ""}, {"name": "Single leg drills", "repeat": 2, "intervals": [{"name": "Single leg Left", "power_zone": "Z2", "cadence": 95, "duration": 30, "notes": ""}, {"name": "Recovery", "power_zone": "Z2", "cadence": null, "duration": 30, "notes": ""}, {"name": "Single leg Right", "power_zone": "Z2", "cadence": 95, "duration": 30, "notes": ""}, {"name": "Recovery", "power_zone": "Z2", "cadence": null, "duration": 30, "notes": ""}]}, {"name": "Recover", "power_zone": "Z1", "cadence": null, "duration": 120, "notes": ""}, {"name": "Overgear", "power_zone": "Z4", "cadence": 65, "duration": 180, "notes": ""}, {"name": "Fast cadence", "power_zone": "Z3", "cadence": 95, "duration": 180, "notes": ""}, {"name": "Recover", "power_zone": "Z1", "cadence": null, "duration": 120, "notes": ""}, {"name": "Fast cadence", "power_zone": "Z5", "cadence": 95, "duration": 30, "notes": ""}, {"name": "Overgear", "power_zone": "Z3", "cadence": 60, "duration": 150, "notes": ""}, {"name": "Recover", "power_zone": "Z1", "cadence": null, "duration": 120, "notes": ""}, {"name": "Overgear", "power_zone": "Z4", "cadence": 65, "duration": 180, "notes": ""}, {"name": "Fast cadence", "power_zone": "Z3", "cadence": 95, "duration": 180, "notes": ""}, {"name": "Recover", "power_zone": "Z1", "cadence": null, "duration": 120, "notes": ""}, {"name": "Fast cadence", "power_zone": "Z5", "cadence": 95, "duration": 30, "notes": ""}, {"name": "Overgear", "power_zone": "Z3", "cadence": 60, "duration": 150, "notes": ""}, {"name": "Recover", "power_zone": "Z1", "cadence": null, "duration": 120, "notes": ""}, {"name": "Z6 Intervals - Set 1", "repeat": 3, "intervals": [{"name": "Fast cadence - Z6", "power_zone": "Z6", "cadence": 95, "duration": 15, "notes": ""}, {"name": "Overgear Recovery", "power_zone": "Z2", "cadence": 60, "duration": 60, "notes": ""}]}, {"name": "Recover", "power_zone": "Z1", "cadence": null, "duration": 60, "notes": ""}, {"name": "Z6 Intervals - Set 2", "repeat": 3, "intervals": [{"name": "Fast cadence - Z6", "power_zone": "Z6", "cadence": 95, "duration": 15, "notes": ""}, {"name": "Overgear Recovery", "power_zone": "Z2", "cadence": 60, "duration": 60, "notes": ""}]}, {"name": "Z2 Cadence 95", "power_zone": "Z2", "cadence": 95, "duration": 120, "notes": ""}, {"name": "Cool-down Z2", "power_zone": "Z2", "cadence": null, "duration": 120, "notes": ""}, {"name": "Cool-down Z1", "power_zone": "Z1", "cadence": null, "duration": 60, "notes": ""}]}